semantic_versioning/__init__.py
python_semantic_versioning-0.1.0a0.dist-info/LICENSE
python_semantic_versioning-0.1.0a0.dist-info/METADATA
python_semantic_versioning-0.1.0a0.dist-info/WHEEL
python_semantic_versioning-0.1.0a0.dist-info/top_level.txt
python_semantic_versioning-0.1.0a0.dist-info/RECORD
