Metadata-Version: 2.1
Name: python-semantic-versioning
Version: 0.1.0a0
Summary: 📌 A simple utility to facilitate Semantic Versioning of Python packages 🐍
Author-email: Kamil Paduszyński <paduszyk@gmail.com>
License: MIT License
Keywords: python,semantic,versioning
Classifier: Development Status :: 2 - Pre-Alpha
Classifier: Intended Audience :: Developers
Classifier: License :: OSI Approved :: MIT License
Classifier: Programming Language :: Python
Classifier: Programming Language :: Python :: 3
Classifier: Topic :: Software Development :: Libraries :: Python Modules
Classifier: Topic :: Software Development :: Version Control
License-File: LICENSE
